bbo/__init__.py
bbo/_approx_hull_ndim.py
bbo/exception.py
bbo/hull.py
bbo/output.py
bbo/pca.py
bbo/typing.py
bbo/util.py
bbo-0.0.2.dist-info/METADATA
bbo-0.0.2.dist-info/WHEEL
bbo-0.0.2.dist-info/top_level.txt
bbo-0.0.2.dist-info/RECORD
